ORIGIN '~beta/basiclib/betaenv';
-- lib: attributes --

nop:				(# exit 0 #);
_nop:                           (# exit nop #);
aconst_null:			(# exit 1 #);
iconst_m1:			(# exit 2 #);
iconst_0:			(# exit 3 #);
iconst_1:			(# exit 4 #);
iconst_2:			(# exit 5 #);
iconst_3:			(# exit 6 #);
iconst_4:			(# exit 7 #);
iconst_5:			(# exit 8 #);
lconst_0:			(# exit 9 #);
lconst_1:			(# exit 10 #);
fconst_0:			(# exit 11 #);
fconst_1:			(# exit 12 #);
fconst_2:			(# exit 13 #);
dconst_0:			(# exit 14 #);
dconst_1:			(# exit 15 #);
bipush:				(# exit 16 #);
sipush:				(# exit 17 #);
ldc:				(# exit 18 #);
ldc_w:				(# exit 19 #);
ldc2_w:				(# exit 20 #);
iload:				(# exit 21 #);
lload:				(# exit 22 #);
fload:				(# exit 23 #);
dload:				(# exit 24 #);
aload:				(# exit 25 #);
iload_0:			(# exit 26 #);
iload_1:			(# exit 27 #);
iload_2:			(# exit 28 #);
iload_3:			(# exit 29 #);
lload_0:			(# exit 30 #);
lload_1:			(# exit 31 #);
lload_2:			(# exit 32 #);
lload_3:			(# exit 33 #);
fload_0:			(# exit 34 #);
fload_1:			(# exit 35 #);
fload_2:			(# exit 36 #);
fload_3:			(# exit 37 #);
dload_0:			(# exit 38 #);
dload_1:			(# exit 39 #);
dload_2:			(# exit 40 #);
dload_3:			(# exit 41 #);
aload_0:			(# exit 42 #);
aload_1:			(# exit 43 #);
aload_2:			(# exit 44 #);
aload_3:			(# exit 45 #);
iaload:				(# exit 46 #);
laload:				(# exit 47 #);
faload:				(# exit 48 #);
daload:				(# exit 49 #);
aaload:				(# exit 50 #);
baload:				(# exit 51 #);
caload:				(# exit 52 #);
saload:				(# exit 53 #);
istore:				(# exit 54 #);
lstore:				(# exit 55 #);
fstore:				(# exit 56 #);
dstore:				(# exit 57 #);
astore:				(# exit 58 #);
istore_0:			(# exit 59 #);
istore_1:			(# exit 60 #);
istore_2:			(# exit 61 #);
istore_3:			(# exit 62 #);
lstore_0:			(# exit 63 #);
lstore_1:			(# exit 64 #);
lstore_2:			(# exit 65 #);
lstore_3:			(# exit 66 #);
fstore_0:			(# exit 67 #);
fstore_1:			(# exit 68 #);
fstore_2:			(# exit 69 #);
fstore_3:			(# exit 70 #);
dstore_0:			(# exit 71 #);
dstore_1:			(# exit 72 #);
dstore_2:			(# exit 73 #);
dstore_3:			(# exit 74 #);
astore_0:			(# exit 75 #);
astore_1:			(# exit 76 #);
astore_2:			(# exit 77 #);
astore_3:			(# exit 78 #);
iastore:			(# exit 79 #);
lastore:			(# exit 80 #);
fastore:			(# exit 81 #);
dastore:			(# exit 82 #);
aastore:			(# exit 83 #);
bastore:			(# exit 84 #);
castore:			(# exit 85 #);
sastore:			(# exit 86 #);
pop:				(# exit 87 #);
_pop:				(# exit pop #);
pop2:				(# exit 88 #);
_pop2:				(# exit pop2 #);
dup:				(# exit 89 #);
_dup:				(# exit dup #);
dup_x1:				(# exit 90 #);
dup_x2:				(# exit 91 #);
dup2:				(# exit 92 #);
dup2_x1:			(# exit 93 #);
dup2_x2:			(# exit 94 #);
swap:				(# exit 95 #);
iadd:				(# exit 96 #);
ladd:				(# exit 97 #);
fadd:				(# exit 98 #);
dadd:				(# exit 99 #);
isub:				(# exit 100 #);
lsub:				(# exit 101 #);
fsub:				(# exit 102 #);
dsub:				(# exit 103 #);
imul:				(# exit 104 #);
lmul:				(# exit 105 #);
fmul:				(# exit 106 #);
dmul:				(# exit 107 #);
idiv:				(# exit 108 #);
ldiv:				(# exit 109 #);
fdiv:				(# exit 110 #);
ddiv:				(# exit 111 #);
irem:				(# exit 112 #);
lrem:				(# exit 113 #);
frem:				(# exit 114 #);
drem:				(# exit 115 #);
ineg:				(# exit 116 #);
lneg:				(# exit 117 #);
fneg:				(# exit 118 #);
dneg:				(# exit 119 #);
ishl:				(# exit 120 #);
lshl:				(# exit 121 #);
ishr:				(# exit 122 #);
lshr:				(# exit 123 #);
iushr:				(# exit 124 #);
lushr_html:			(# exit 125 #);
iand:				(# exit 126 #);
land:				(# exit 127 #);
ior:				(# exit 128 #);
lor:				(# exit 129 #);
ixor:				(# exit 130 #);
lxor:				(# exit 131 #);
iinc:				(# exit 132 #);
i2l:				(# exit 133 #);
i2f:				(# exit 134 #);
i2d:				(# exit 135 #);
l2i:				(# exit 136 #);
l2f:				(# exit 137 #);
l2d:				(# exit 138 #);
f2i:				(# exit 139 #);
f2l:				(# exit 140 #);
f2d:				(# exit 141 #);
d2i:				(# exit 142 #);
d2l:				(# exit 143 #);
d2f:				(# exit 144 #);
i2b:				(# exit 145 #);
i2c:				(# exit 146 #);
i2s:				(# exit 147 #);
lcmp:				(# exit 148 #);
fcmpl:				(# exit 149 #);
fcmpg:				(# exit 150 #);
dcmpl:				(# exit 151 #);
dcmpg:				(# exit 152 #);
ifeq:				(# exit 153 #);
ifne:				(# exit 154 #);
iflt:				(# exit 155 #);
ifge:				(# exit 156 #);
ifgt:				(# exit 157 #);
ifle:				(# exit 158 #);
if_icmpeq:			(# exit 159 #);
if_icmpne:			(# exit 160 #);
if_icmplt:			(# exit 161 #);
if_icmpge:			(# exit 162 #);
if_icmpgt:			(# exit 163 #);
if_icmple:			(# exit 164 #);
if_acmpeq:			(# exit 165 #);
if_acmpne:			(# exit 166 #);
goto:				(# exit 167 #);
jsr:				(# exit 168 #);
ret:				(# exit 169 #);
tableswitch:			(# exit 170 #);
lookupswitch:			(# exit 171 #);
ireturn:			(# exit 172 #);
lreturn:			(# exit 173 #);
freturn:			(# exit 174 #);
dreturn:			(# exit 175 #);
areturn:			(# exit 176 #);
return:				(# exit 177 #);
_return:			(# exit return #);
getstatic:			(# exit 178 #);
putstatic:			(# exit 179 #);
getfield:			(# exit 180 #);
putfield:			(# exit 181 #);
invokevirtual:			(# exit 182 #);
invokespecial:			(# exit 183 #);
invokestatic:			(# exit 184 #);
(*invokenonvirtual:               (# exit invokestatic #); (* CHECK *)
invokeinterface:		(# exit 185 #);
Unused1:			(# exit 186 #);
new:				(# exit 187 #);
newarray:			(# exit 188 #);
anewarray:			(# exit 189 #);
arraylength:			(# exit 190 #);
athrow:				(# exit 191 #);
checkcast:			(# exit 192 #);
instanceof:			(# exit 193 #);
monitorenter:			(# exit 194 #);
monitorexit:			(# exit 195 #);
wide:				(# exit 196 #);
multianewarray:			(# exit 197 #);
ifnull:				(# exit 198 #);
ifnonnull:			(# exit 199 #);
goto_w:				(# exit 200 #);
jsr_w:				(# exit 201 #);
breakpoint:			(# exit 202 #);
ldc_quick:			(# exit 203 #);
Unused2:			(# exit 204 #);
ldc2_quick:			(# exit 205 #);
getfield_quick:			(# exit 206 #);
putfield_quick:			(# exit 207 #);
getfield2_quick:		(# exit 208 #);
putfield2_quick:		(# exit 209 #);
Unused3:			(# exit 210 #);
putstatic__quick:		(# exit 211 #);
getstatic2_quick:		(# exit 212 #);
putstatic2_quick:		(# exit 213 #);
invokevirtual_quick:		(# exit 214 #);
invokenonvirtual_quick:		(# exit 215 #);
invokesuper_quick:		(# exit 216 #);
invokestatic_quick:		(# exit 217 #);
invokeinterface_quick:		(# exit 218 #);
invokevirtualobject_quick:	(# exit 219 #);
Unused4:			(# exit 220 #);
new_quick:			(# exit 221 #);
anewarray_quick:		(# exit 222 #);
multianewarray_quick:		(# exit 223 #);
checkcast_quick:		(# exit 224 #);
instanceof_quick:		(# exit 225 #);
invokevirtual_quick_w:		(# exit 226 #);
getfield_quick_w:		(# exit 227 #);
putfield_quick_w:		(# exit 228 #);
Unused5:			(# exit 229 #);
Unused6:			(# exit 230 #);
Unused7:			(# exit 231 #);
Unused8:			(# exit 232 #);
Unused9:			(# exit 233 #);
Unused10:			(# exit 234 #);
Unused11:			(# exit 235 #);
Unused12:			(# exit 236 #);
Unused13:			(# exit 237 #);
Unused14:			(# exit 238 #);
Unused15:			(# exit 239 #);
Unused16:			(# exit 240 #);
Unused17:			(# exit 241 #);
Unused18:			(# exit 242 #);
Unused19:			(# exit 243 #);
Unused20:			(# exit 244 #);
Unused21:			(# exit 245 #);
Unused22:			(# exit 246 #);
Unused23:			(# exit 247 #);
Unused24:			(# exit 248 #);
Unused25:			(# exit 249 #);
Unused26:			(# exit 250 #);
Unused27:			(# exit 251 #);
Unused28:			(# exit 252 #);
Unused29:			(# exit 253 #);
impdep1:			(# exit 254 #);
impdep2:			(# exit 255 #);

(* Array types *)
T_BOOLEAN: (# exit 4 #);
T_CHAR: (# exit 5 #);
T_FLOAT: (# exit 6 #);
T_DOUBLE: (# exit 7 #);
T_BYTE: (# exit 8 #);
T_SHORT: (# exit 9 #);
T_INT: (# exit 10 #);
T_LONG: (# exit 11 #);
